pysible/__init__.py
pysible/__main__.py
pysible/cli.py
pysible/core/__init__.py
pysible/core/auth.py
pysible/core/pyrate.py
pysible/core/rbac.py
pysible/core/token.py
pysible/database/__init__.py
pysible/database/db.py
pysible/database/redis_client.py
pysible/logger/__init__.py
pysible/logger/logger.py
pysible-0.1.1.dist-info/licenses/LICENSE
pysible-0.1.1.dist-info/METADATA
pysible-0.1.1.dist-info/WHEEL
pysible-0.1.1.dist-info/entry_points.txt
pysible-0.1.1.dist-info/top_level.txt
pysible-0.1.1.dist-info/RECORD
