Metadata-Version: 2.4
Name: pysible
Version: 0.1.1
Summary: Security library for FastAPI (RBAC, rate limiting, jwtAuth etc.)
Author-email: Akshat Mishra <mails.akshat@gmail.com>
License: MIT
Project-URL: Homepage, https://github.com/AKSHATM99/pysible.git
License-File: LICENSE
Requires-Dist: typer[all]
Requires-Dist: redis
Requires-Dist: fastapi[standard]
Requires-Dist: python-jose
Requires-Dist: python-dotenv
Dynamic: license-file
